llm_playground/__about__.py
llm_playground/__init__.py
llm_playground/cli.py
llm_playground/core.py
llm_playground-0.0.1.dist-info/METADATA
llm_playground-0.0.1.dist-info/WHEEL
llm_playground-0.0.1.dist-info/entry_points.txt
llm_playground-0.0.1.dist-info/licenses/LICENSE.txt
llm_playground-0.0.1.dist-info/RECORD
